{
  "fonts": [
    {
      "id": "ivy",
      "src": [
        {
          "path": "../node_modules/@axonivy/ui-icons/src-gen/ivy-icons.woff2",
          "format": "woff2"
        }
      ],
      "weight": "normal",
      "style": "normal",
      "size": "120%"
    }
  ],
  "iconDefinitions": {
    "_default_light": {
      "fontCharacter": "\\f141",
      "fontColor": "#bfc2c1"
    },
    "_default": {
      "fontCharacter": "\\f141",
      "fontColor": "#d4d7d6"
    },
    "_folder_light": {
      "fontCharacter": "\\f145",
      "fontColor": "#bfc2c1"
    },
    "_folder": {
      "fontCharacter": "\\f145",
      "fontColor": "#d4d7d6"
    },
    "_html_light": {
      "fontCharacter": "\\f182",
      "fontColor": "#bfc2c1"
    },
    "_html": {
      "fontCharacter": "\\f182",
      "fontColor": "#d4d7d6"
    },
    "_xml_light": {
      "fontCharacter": "\\f18b",
      "fontColor": "#bfc2c1"
    },
    "_xml": {
      "fontCharacter": "\\f18b",
      "fontColor": "#d4d7d6"
    },
    "_image_light": {
      "fontCharacter": "\\f126",
      "fontColor": "#bfc2c1"
    },
    "_image": {
      "fontCharacter": "\\f126",
      "fontColor": "#d4d7d6"
    },
    "_java_light": {
      "fontCharacter": "\\f128",
      "fontColor": "#bfc2c1"
    },
    "_java": {
      "fontCharacter": "\\f128",
      "fontColor": "#d4d7d6"
    },
    "_ivy_process": {
      "fontCharacter": "\\f16c",
      "fontColor": "#d4d7d6",
      "fontId": "ivy"
    },
    "_ivy_process_light": {
      "fontCharacter": "\\f16c",
      "fontColor": "#bfc2c1",
      "fontId": "ivy"
    },
    "_ivy_dataclass": {
      "fontCharacter": "\\f12b",
      "fontColor": "#d4d7d6",
      "fontId": "ivy"
    },
    "_ivy_dataclass_light": {
      "fontCharacter": "\\f12b",
      "fontColor": "#bfc2c1",
      "fontId": "ivy"
    },
    "_ivy_form": {
      "fontCharacter": "\\f141",
      "fontColor": "#d4d7d6",
      "fontId": "ivy"
    },
    "_ivy_form_light": {
      "fontCharacter": "\\f141",
      "fontColor": "#bfc2c1",
      "fontId": "ivy"
    },
    "_ivy_casemap": {
      "fontCharacter": "\\f116",
      "fontColor": "#d4d7d6",
      "fontId": "ivy"
    },
    "_ivy_casemap_light": {
      "fontCharacter": "\\f116",
      "fontColor": "#bfc2c1",
      "fontId": "ivy"
    },
    "_ivy_cms": {
      "fontCharacter": "\\f120",
      "fontColor": "#d4d7d6",
      "fontId": "ivy"
    },
    "_ivy_cms_light": {
      "fontCharacter": "\\f120",
      "fontColor": "#bfc2c1",
      "fontId": "ivy"
    },
    "_ivy_databases": {
      "fontCharacter": "\\f12b",
      "fontColor": "#d4d7d6",
      "fontId": "ivy"
    },
    "_ivy_databases_light": {
      "fontCharacter": "\\f12b",
      "fontColor": "#bfc2c1",
      "fontId": "ivy"
    },
    "_ivy_persistence": {
      "fontCharacter": "\\f129",
      "fontColor": "#d4d7d6",
      "fontId": "ivy"
    },
    "_ivy_persistence_light": {
      "fontCharacter": "\\f129",
      "fontColor": "#bfc2c1",
      "fontId": "ivy"
    },
    "_ivy_restclients": {
      "fontCharacter": "\\f176",
      "fontColor": "#d4d7d6",
      "fontId": "ivy"
    },
    "_ivy_restclients_light": {
      "fontCharacter": "\\f176",
      "fontColor": "#bfc2c1",
      "fontId": "ivy"
    },
    "_ivy_roles": {
      "fontCharacter": "\\f194",
      "fontColor": "#d4d7d6",
      "fontId": "ivy"
    },
    "_ivy_roles_light": {
      "fontCharacter": "\\f194",
      "fontColor": "#bfc2c1",
      "fontId": "ivy"
    },
    "_ivy_users": {
      "fontCharacter": "\\f193",
      "fontColor": "#d4d7d6",
      "fontId": "ivy"
    },
    "_ivy_users_light": {
      "fontCharacter": "\\f193",
      "fontColor": "#bfc2c1",
      "fontId": "ivy"
    },
    "_ivy_variables": {
      "fontCharacter": "\\f195",
      "fontColor": "#d4d7d6",
      "fontId": "ivy"
    },
    "_ivy_variables_light": {
      "fontCharacter": "\\f195",
      "fontColor": "#bfc2c1",
      "fontId": "ivy"
    },
    "_ivy_webservices": {
      "fontCharacter": "\\f19b",
      "fontColor": "#d4d7d6",
      "fontId": "ivy"
    },
    "_ivy_webservices_light": {
      "fontCharacter": "\\f19b",
      "fontColor": "#bfc2c1",
      "fontId": "ivy"
    }
  },
  "file": "_default",
  "folder": "_folder",
  "fileExtensions": {
    "avif": "_image",
    "gif": "_image",
    "jpg": "_image",
    "jpeg": "_image",
    "png": "_image",
    "pxm": "_image",
    "svgx": "_image",
    "tiff": "_image",
    "webp": "_image",
    "p.json": "_ivy_process",
    "d.json": "_ivy_dataclass",
    "f.json": "_ivy_form",
    "m.json": "_ivy_casemap",
    "cms/yaml": "_ivy_cms"
  },
  "fileNames": {
    "databases.yaml": "_ivy_databases",
    "persistence.yaml": "_ivy_persistence",
    "rest-clients.yaml": "_ivy_restclients",
    "roles.yaml": "_ivy_roles",
    "users.yaml": "_ivy_users",
    "variables.yaml": "_ivy_variables",
    "webservice-clients.yaml": "_ivy_webservices"
  },
  "languageIds": {
    "html": "_html",
    "xml": "_xml"
  },
  "light": {
    "file": "_default_light",
    "folder": "_folder_light",
    "fileExtensions": {
      "avif": "_image_light",
      "gif": "_image_light",
      "jpg": "_image_light",
      "jpeg": "_image_light",
      "png": "_image_light",
      "pxm": "_image_light",
      "svgx": "_image_light",
      "tiff": "_image_light",
      "webp": "_image_light",
      "p.json": "_ivy_process_light",
      "d.json": "_ivy_dataclass_light",
      "f.json": "_ivy_form_light",
      "m.json": "_ivy_casemap_light",
      "cms/yaml": "_ivy_cms_light"
    },
    "languageIds": {
      "html": "_html_light",
      "xml": "_xml_light"
    },
    "fileNames": {
      "databases.yaml": "_ivy_databases_light",
      "persistence.yaml": "_ivy_persistence_light",
      "rest-clients.yaml": "_ivy_restclients_light",
      "roles.yaml": "_ivy_roles_light",
      "users.yaml": "_ivy_users_light",
      "variables.yaml": "_ivy_variables_light",
      "webservice-clients.yaml": "_ivy_webservices_light"
    }
  }
}
